Metadata-Version: 1.1
Name: django-class-based-auth-views-jp
Version: 0.3.1
Summary: A reimplementation of django.contrib.auth.views as class based views.
Home-page: http://github.com/jperelli/django-class-based-auth-views
Author: Julian Perelli
Author-email: jperelli@gmail.com
License: BSD
Platform: OS Independent
Classifier: Development Status :: 3 - Alpha
Classifier: Framework :: Django
Classifier: Intended Audience :: Developers
Classifier: License :: OSI Approved :: BSD License
Classifier: Operating System :: OS Independent
Classifier: Programming Language :: Python
Classifier: Topic :: Internet :: WWW/HTTP
